gpg_lite/__init__.py
gpg_lite/cmd.py
gpg_lite/deserialize.py
gpg_lite/keyserver.py
gpg_lite/model.py
gpg_lite/parser.py
gpg_lite/py.typed
gpg_lite/store.py
gpg_lite/version.py
gpg_lite-0.12.3.dist-info/AUTHORS.md
gpg_lite-0.12.3.dist-info/LICENSE
gpg_lite-0.12.3.dist-info/METADATA
gpg_lite-0.12.3.dist-info/WHEEL
gpg_lite-0.12.3.dist-info/top_level.txt
gpg_lite-0.12.3.dist-info/RECORD
