Metadata-Version: 2.1
Name: gpg-lite
Version: 0.12.3
Summary: python gpg bindings
Home-page: https://gitlab.com/biomedit/gpg-lite
Author: Jaroslaw Surkont, Gerhard Bräunlich, Robin Engler, Christian Ribeaud, François Martin, Simone Guzzi
Author-email: jaroslaw.surkont@unibas.ch, gerhard.braeunlich@id.ethz.ch, robin.engler@sib.swiss, christian.ribeaud@karakun.com, francois.martin@karakun.com, simone.guzzi@sib.swiss
License: LGPL3
Project-URL: Source, https://gitlab.com/biomedit/gpg-lite/
Classifier: Programming Language :: Python :: 3
Classifier: Programming Language :: Python :: 3.7
Classifier: Programming Language :: Python :: 3.8
Classifier: Programming Language :: Python :: 3.9
Classifier: Programming Language :: Python :: 3.10
Classifier: Programming Language :: Python :: 3.11
Classifier: License :: OSI Approved :: GNU Lesser General Public License v3 (LGPLv3)
Classifier: Operating System :: OS Independent
Requires-Python: >=3.7
License-File: LICENSE
License-File: AUTHORS.md
Provides-Extra: test
Requires-Dist: pytest ; extra == 'test'
